LICENSE.txt
MANIFEST.in
README.md
demjson3.py
jsonlint
setup.py
demjson3.egg-info/PKG-INFO
demjson3.egg-info/SOURCES.txt
demjson3.egg-info/dependency_links.txt
demjson3.egg-info/top_level.txt
docs/CHANGES.txt
docs/HOOKS.txt
docs/INSTALL.txt
docs/NEWS.txt
docs/PYTHON3.txt
docs/demjson3.txt
docs/jsonlint.txt
test/test_demjson3.py