Metadata-Version: 2.1
Name: demjson3
Version: 3.0.5
Summary: encoder, decoder, and lint/validator for JSON (JavaScript Object Notation) compliant with RFC 7159
Home-page: UNKNOWN
Author: Deron Meranda
Author-email: deron.meranda@gmail.com
License: GNU LGPL 3.0
Keywords: JSON,jsonlint,JavaScript,UTF-32
Platform: UNKNOWN
Classifier: Development Status :: 4 - Beta
Classifier: Intended Audience :: Developers
Classifier: License :: OSI Approved :: GNU Library or Lesser General Public License (LGPL)
Classifier: Operating System :: OS Independent
Classifier: Programming Language :: Python :: 3.6
Classifier: Programming Language :: Python :: 3.7
Classifier: Programming Language :: Python :: 3.8
Classifier: Topic :: Software Development :: Libraries :: Python Modules
Classifier: Topic :: Internet :: WWW/HTTP :: Dynamic Content
License-File: LICENSE.txt
